Metadata-Version: 2.1
Name: gittivity
Version: 1.0.0
Summary: Git activity terminal notifier
Home-page: https://github.com/s1s1ty/gittivity/
Author: Shaonty Dutta
Author-email: shaonty.dutta@gmail.com
License: MIT
Keywords: Utilities,Terminal,Notifier
Platform: UNKNOWN
Classifier: Development Status :: 4 - Beta
Classifier: Intended Audience :: Developers
Classifier: Natural Language :: English
Classifier: Topic :: Utilities
Classifier: Topic :: Terminals
Classifier: Programming Language :: Python :: 2
Classifier: Programming Language :: Python :: 3
